filanti/__init__.py
filanti/__main__.py
filanti/api/__init__.py
filanti/api/sdk.py
filanti/cli/__init__.py
filanti/cli/main.py
filanti/core/__init__.py
filanti/core/errors.py
filanti/core/file_manager.py
filanti/core/metadata.py
filanti/core/plugins.py
filanti/core/secrets.py
filanti/core/secure_memory.py
filanti/crypto/__init__.py
filanti/crypto/asymmetric.py
filanti/crypto/decryption.py
filanti/crypto/encryption.py
filanti/crypto/kdf.py
filanti/crypto/key_management.py
filanti/crypto/streaming.py
filanti/hashing/__init__.py
filanti/hashing/crypto_hash.py
filanti/integrity/__init__.py
filanti/integrity/checksum.py
filanti/integrity/mac.py
filanti/integrity/signature.py
filanti-1.0.0.dist-info/METADATA
filanti-1.0.0.dist-info/WHEEL
filanti-1.0.0.dist-info/entry_points.txt
filanti-1.0.0.dist-info/licenses/LICENSE
filanti-1.0.0.dist-info/RECORD
