Metadata-Version: 2.4
Name: filanti
Version: 1.0.0
Summary: A modular, security-focused file framework for encryption, hashing, and integrity verification
License: MIT
License-File: LICENSE
Keywords: encryption,decryption,hashing,security,cryptography,file-integrity,aes-gcm,chacha20,argon2,hmac,digital-signatures,ed25519
Author: Decliqe
Maintainer: Decliqe
Requires-Python: >=3.11
Classifier: Development Status :: 5 - Production/Stable
Classifier: Intended Audience :: Developers
Classifier: Intended Audience :: Information Technology
Classifier: Intended Audience :: System Administrators
Classifier: License :: OSI Approved :: MIT License
Classifier: Operating System :: OS Independent
Classifier: Programming Language :: Python :: 3
Classifier: Programming Language :: Python :: 3.11
Classifier: Programming Language :: Python :: 3.12
Classifier: Programming Language :: Python :: 3.13
Classifier: Programming Language :: Python :: 3.14
Classifier: Topic :: Security
Classifier: Topic :: Security :: Cryptography
Classifier: Topic :: System :: Filesystems
Classifier: Typing :: Typed
Requires-Dist: argon2-cffi (>=23.1.0)
Requires-Dist: cryptography (>=42.0.0)
Requires-Dist: typer (>=0.9.0)
